OpenOB-4.0.3.data/scripts/openob
openob/__init__.py
openob/audio_interface.py
openob/link_config.py
openob/logger.py
openob/node.py
openob/rtp/__init__.py
openob/rtp/rx.py
openob/rtp/tx.py
OpenOB-4.0.3.dist-info/METADATA
OpenOB-4.0.3.dist-info/WHEEL
OpenOB-4.0.3.dist-info/top_level.txt
OpenOB-4.0.3.dist-info/RECORD
