Metadata-Version: 2.1
Name: OpenOB
Version: 4.0.3
Summary: Broadcast audio over IP codec built with PyGST
Home-page: https://github.com/JamesHarrison/openob
Author: James Harrison
Author-email: james@talkunafraid.co.uk
License: UNKNOWN
Platform: UNKNOWN
Classifier: Programming Language :: Python
Classifier: Programming Language :: Python :: 3
Classifier: Programming Language :: Python :: 2
Classifier: License :: OSI Approved :: BSD License
Classifier: Natural Language :: English
Classifier: Operating System :: POSIX :: Linux
Classifier: Topic :: Communications
Classifier: Topic :: Internet
Classifier: Topic :: Software Development :: Libraries :: Python Modules
Classifier: Development Status :: 5 - Production/Stable
Classifier: Environment :: Console
Classifier: Environment :: No Input/Output (Daemon)
Classifier: Intended Audience :: Telecommunications Industry
Classifier: Intended Audience :: System Administrators
Classifier: Intended Audience :: Developers
Requires-Dist: redis
